convertdate/__init__.py
convertdate/armenian.py
convertdate/bahai.py
convertdate/coptic.py
convertdate/daycount.py
convertdate/dublin.py
convertdate/french_republican.py
convertdate/gregorian.py
convertdate/hebrew.py
convertdate/holidays.py
convertdate/indian_civil.py
convertdate/islamic.py
convertdate/iso.py
convertdate/julian.py
convertdate/julianday.py
convertdate/mayan.py
convertdate/ordinal.py
convertdate/persian.py
convertdate/positivist.py
convertdate/utils.py
convertdate/data/__init__.py
convertdate/data/french_republican_days.py
convertdate/data/positivist.py
convertdate-2.3.2.dist-info/LICENSE
convertdate-2.3.2.dist-info/METADATA
convertdate-2.3.2.dist-info/WHEEL
convertdate-2.3.2.dist-info/top_level.txt
convertdate-2.3.2.dist-info/zip-safe
convertdate-2.3.2.dist-info/RECORD
