Metadata-Version: 2.1
Name: convertdate
Version: 2.3.2
Summary: Converts between Gregorian dates and other calendar systems.Calendars included: Baha'i, French Republican, Hebrew, Indian Civil, Islamic, ISO, Julian, Mayan and Persian.
Home-page: https://github.com/fitnr/convertdate
Author: Neil Freeman
Author-email: contact@fakeisthenewreal.org
License: MIT
Platform: UNKNOWN
Classifier: Programming Language :: Python
Classifier: Programming Language :: Python :: 3
Classifier: Programming Language :: Python :: 3.5
Classifier: Programming Language :: Python :: 3.6
Classifier: Programming Language :: Python :: 3.7
Classifier: Programming Language :: Python :: 3.8
Classifier: Programming Language :: Python :: 3.9
Classifier: Topic :: Religion
Classifier: Topic :: Scientific/Engineering :: Astronomy
Classifier: Operating System :: OS Independent
Classifier: License :: OSI Approved :: MIT License
Requires-Python: >=3.5
Provides-Extra: test
Provides-Extra: docs
